{
  "variants": {
    "part=foot,facing=west": {
      "model": "ilikewood:block/bed/foot/lime/birch",
      "y": 270,
      "uvlock": false
    },
    "part=foot,facing=south": {
      "model": "ilikewood:block/bed/foot/lime/birch",
      "y": 180,
      "uvlock": false
    },
    "part=head,facing=south": {
      "model": "ilikewood:block/bed/head/lime/birch",
      "y": 180,
      "uvlock": false
    },
    "part=foot,facing=east": {
      "model": "ilikewood:block/bed/foot/lime/birch",
      "y": 90,
      "uvlock": false
    },
    "part=head,facing=north": {
      "model": "ilikewood:block/bed/head/lime/birch",
      "y": 0,
      "uvlock": false
    },
    "part=head,facing=east": {
      "model": "ilikewood:block/bed/head/lime/birch",
      "y": 90,
      "uvlock": false
    },
    "part=head,facing=west": {
      "model": "ilikewood:block/bed/head/lime/birch",
      "y": 270,
      "uvlock": false
    },
    "part=foot,facing=north": {
      "model": "ilikewood:block/bed/foot/lime/birch",
      "y": 0,
      "uvlock": false
    }
  }
}